{
  "input_file": "F:\\data\\vstrender\\test_input.wav",
  "output_file": "F:\\data\\vstrender\\test_output_sd.wav",
  "sample_rate": 44100,
  "buffer_size": 512,
  "plugins": [
    {
      "path": "C:\\Program Files\\Common Files\\VST3\\Sound Delay.vst3",
      "plugin_name": "Sound Delay",
      "export_parameters_before": "F:\\data\\vstrender\\parameters_before5.json",
      "export_parameters_after": "F:\\data\\vstrender\\parameters_after5.json",
      "parameters": {
        "Bypass": 0.0
      }
    }
  ]
}
